speasy/__init__.py
speasy/config/__init__.py
speasy/core/__init__.py
speasy/core/algorithms.py
speasy/core/any_files.py
speasy/core/data_containers.py
speasy/core/dataprovider.py
speasy/core/datetime_range.py
speasy/core/http.py
speasy/core/platform.py
speasy/core/span_utils.py
speasy/core/time.py
speasy/core/typing.py
speasy/core/url_utils.py
speasy/core/cache/__init__.py
speasy/core/cache/_function_cache.py
speasy/core/cache/_instance.py
speasy/core/cache/_providers_caches.py
speasy/core/cache/_request_locker.py
speasy/core/cache/cache.py
speasy/core/cache/version.py
speasy/core/cdf/__init__.py
speasy/core/cdf/inventory_extractor.py
speasy/core/codecs/__init__.py
speasy/core/codecs/codec_interface.py
speasy/core/codecs/codecs_registry.py
speasy/core/codecs/bundled_codecs/__init__.py
speasy/core/codecs/bundled_codecs/istp_cdf.py
speasy/core/codecs/bundled_codecs/hapi_csv/__init__.py
speasy/core/codecs/bundled_codecs/hapi_csv/codec.py
speasy/core/codecs/bundled_codecs/hapi_csv/csv_file.py
speasy/core/codecs/bundled_codecs/hapi_csv/reader.py
speasy/core/codecs/bundled_codecs/hapi_csv/writer.py
speasy/core/direct_archive_downloader/__init__.py
speasy/core/direct_archive_downloader/direct_archive_downloader.py
speasy/core/impex/__init__.py
speasy/core/impex/client.py
speasy/core/impex/exceptions.py
speasy/core/impex/parser.py
speasy/core/impex/utils.py
speasy/core/index/__init__.py
speasy/core/index/speasy_index.py
speasy/core/inventory/__init__.py
speasy/core/inventory/indexes.py
speasy/core/proxy/__init__.py
speasy/core/requests_scheduling/__init__.py
speasy/core/requests_scheduling/request_dispatch.py
speasy/core/requests_scheduling/split_large_requests.py
speasy/data/archive/cda.yaml
speasy/data/archive/themis_cdpp.yaml.example
speasy/data_providers/__init__.py
speasy/data_providers/amda/__init__.py
speasy/data_providers/amda/ws.py
speasy/data_providers/cda/__init__.py
speasy/data_providers/cda/_direct_archive.py
speasy-1.7.1.dist-info/licenses/LICENSE
speasy-1.7.1.dist-info/WHEEL
speasy-1.7.1.dist-info/METADATA
speasy-1.7.1.dist-info/RECORD
