Metadata-Version: 2.4
Name: speasy
Version: 1.7.1
Summary: A simple Python package to deal with main Space Physics WebServices (CDA, CSA, AMDA and SSC).
Keywords: satellite,plasma-physics,nasa-data,amda,cdpp,CDF
Author-email: Alexis Jeandet <alexis.jeandet@member.fsf.org>
Maintainer-email: Alexis Jeandet <alexis.jeandet@member.fsf.org>
Requires-Python: >=3.9
Classifier: Development Status :: 5 - Production/Stable
Classifier: Intended Audience :: Science/Research
Classifier: Topic :: Scientific/Engineering :: Physics
Classifier: License :: OSI Approved :: MIT License
Classifier: Natural Language :: English
Classifier: Programming Language :: Python :: 3
Classifier: Programming Language :: Python :: 3.9
Classifier: Programming Language :: Python :: 3.10
Classifier: Programming Language :: Python :: 3.11
Classifier: Programming Language :: Python :: 3.12
Classifier: Programming Language :: Python :: 3.13
Classifier: Programming Language :: Python :: 3.14
License-File: LICENSE
Requires-Dist: PyYAML
Requires-Dist: appdirs
Requires-Dist: astropy
Requires-Dist: astroquery
Requires-Dist: diskcache
Requires-Dist: humanize
Requires-Dist: matplotlib
Requires-Dist: numpy
Requires-Dist: packaging
Requires-Dist: pandas
Requires-Dist: pyistp>=0.7.2
Requires-Dist: python-dateutil
Requires-Dist: requests
Requires-Dist: scipy
Requires-Dist: tqdm
Requires-Dist: urllib3>=1.26.0
Requires-Dist: certifi
Requires-Dist: pysocks
Requires-Dist: pyzstd ; extra == "zstd"
Project-URL: homepage, https://github.com/SciQLop/speasy
Provides-Extra: zstd
